README.rst
setup.py
animemon/__init__.py
animemon/animemon.py
animemon.egg-info/PKG-INFO
animemon.egg-info/SOURCES.txt
animemon.egg-info/dependency_links.txt
animemon.egg-info/entry_points.txt
animemon.egg-info/requires.txt
animemon.egg-info/top_level.txt