Metadata-Version: 1.1
Name: animemon
Version: 0.1.1
Summary: Everything about your anime within the command line.
Home-page: https://github.com/nims11/animemon
Author: Nimesh Ghelani
Author-email: nimeshghelani@gmail.com
License: MIT
Keywords: anime,CLI,anime-within-CLI,python
Platform: UNKNOWN
Classifier: Environment :: Console
Classifier: License :: OSI Approved :: MIT License
Classifier: Operating System :: MacOS :: MacOS X
Classifier: Operating System :: Unix
Classifier: Operating System :: POSIX
Classifier: Programming Language :: Python
Classifier: Programming Language :: Python :: 2.7
Classifier: Programming Language :: Python :: 3.4
Classifier: Topic :: Utilities
Classifier: Topic :: Software Development :: Libraries :: Python Modules
Classifier: Topic :: Software Development :: User Interfaces
Classifier: Topic :: Software Development :: Version Control
